lens/__init__.py
lens/actor/__init__.py
lens/actor/actor.py
lens/actor/boot.py
lens/actor/control.py
lens/actor/emitter.py
lens/actor/event.py
lens/actor/filepath.py
lens/actor/inner.py
lens/actor/outer.py
lens/actor/process.py
lens/actor/shepherd.py
lens/actor/stub.py
lens/analysis/__init__.py
lens/analysis/analysis.py
lens/analysis/analyze_compartment.py
lens/analysis/analyze_lattice.py
lens/analysis/chemotaxis_trace.py
lens/analysis/multigen_compartment.py
lens/analysis/run_analysis.py
lens/analysis/snapshots.py
lens/data/__init__.py
lens/data/helper.py
lens/data/knowledge_base.py
lens/data/spreadsheets.py
lens/data/flat/__init__.py
lens/data/flat/covert2002_GLC_G6P_flux_bounds.tsv
lens/data/flat/covert2002_ecoli_metabolism_met_mw.tsv
lens/data/flat/covert2002_exchange_fluxes.tsv
lens/data/flat/covert2002_maintenance_biomass_fluxes.tsv
lens/data/flat/covert2002_reactions.tsv
lens/data/flat/covert2002_regulatory_proteins.tsv
lens/data/flat/covert2002_transport.tsv
lens/data/flat/lookup_conc_minimal.tsv
lens/data/flat/lookup_conc_minimal_minus_oxygen.tsv
lens/data/flat/lookup_conc_minimal_plus_amino_acids.tsv
lens/data/flat/lookup_flux_minimal.tsv
lens/data/flat/lookup_flux_minimal_minus_oxygen.tsv
lens/data/flat/lookup_flux_minimal_plus_amino_acids.tsv
lens/data/flat/media_recipes.tsv
lens/data/flat/timelines_def.tsv
lens/data/flat/wcEcoli_biomass.tsv
lens/data/flat/wcEcoli_complexationReactions.tsv
lens/data/flat/wcEcoli_environment_molecules.tsv
lens/data/flat/wcEcoli_proteins.tsv
lens/data/flat/wcEcoli_reactions.tsv
lens/data/flat/wcEcoli_transport_reactions.tsv
lens/data/flat/media/5X_supplement_EZ.tsv
lens/data/flat/media/GLC_G6P.tsv
lens/data/flat/media/GLC_LCT.tsv
lens/data/flat/media/M9.tsv
lens/data/flat/media/M9_GLC.tsv
lens/data/flat/media/wcEcoli_base.tsv
lens/data/json_files/__init__.py
lens/data/json_files/kinetic_rate_laws_example.json
lens/environment/__init__.py
lens/environment/boot.py
lens/environment/control.py
lens/environment/lattice.py
wholecell_lens-0.0.28.dist-info/LICENSE
wholecell_lens-0.0.28.dist-info/METADATA
wholecell_lens-0.0.28.dist-info/WHEEL
wholecell_lens-0.0.28.dist-info/entry_points.txt
wholecell_lens-0.0.28.dist-info/top_level.txt
wholecell_lens-0.0.28.dist-info/RECORD
